simpleOutlierRemoval/__init__.py
simpleOutlierRemoval/main.py
simpleOutlierRemoval-0.0.2.dist-info/LICENSE
simpleOutlierRemoval-0.0.2.dist-info/METADATA
simpleOutlierRemoval-0.0.2.dist-info/WHEEL
simpleOutlierRemoval-0.0.2.dist-info/top_level.txt
simpleOutlierRemoval-0.0.2.dist-info/RECORD
