Metadata-Version: 2.1
Name: simpleOutlierRemoval
Version: 0.0.2
Summary: For a series with assuming normal distribution, removal of outlier
Home-page: https://github.com/arjunjanamatti/simpleOutlierRemoval
Author: Arjun Janamatti
Author-email: arjunjanamatti@gmail.com
Classifier: Programming Language :: Python :: 3
Classifier: License :: OSI Approved :: MIT License
Classifier: Operating System :: OS Independent
Requires-Python: >=3.7
License-File: LICENSE
